<karma>
  <summaries>
    <summary>
      <alias>comment</alias>
      <memberId>5115</memberId>
      <performed>0</performed>
      <received>3</received>
    </summary>
    <summary>
      <alias>comment</alias>
      <memberId>5115</memberId>
      <performed>12</performed>
      <received>0</received>
    </summary>
    <summary>
      <alias>topic</alias>
      <memberId>5115</memberId>
      <performed>5</performed>
      <received>0</received>
    </summary>
  </summaries>
  <histories>
    <history>
      <id>9239</id>
      <alias>comment</alias>
      <memberId>5115</memberId>
      <performed>0</performed>
      <received>1</received>
    </history>
    <history>
      <id>12478</id>
      <alias>comment</alias>
      <memberId>5115</memberId>
      <performed>0</performed>
      <received>1</received>
    </history>
    <history>
      <id>12478</id>
      <alias>comment</alias>
      <memberId>5115</memberId>
      <performed>0</performed>
      <received>1</received>
    </history>
    <history>
      <id>9182</id>
      <alias>comment</alias>
      <memberId>5115</memberId>
      <performed>0</performed>
      <received>0</received>
    </history>
    <history>
      <id>9184</id>
      <alias>comment</alias>
      <memberId>5115</memberId>
      <performed>0</performed>
      <received>0</received>
    </history>
    <history>
      <id>9199</id>
      <alias>comment</alias>
      <memberId>5115</memberId>
      <performed>0</performed>
      <received>0</received>
    </history>
    <history>
      <id>9216</id>
      <alias>comment</alias>
      <memberId>5115</memberId>
      <performed>0</performed>
      <received>0</received>
    </history>
    <history>
      <id>9217</id>
      <alias>comment</alias>
      <memberId>5115</memberId>
      <performed>0</performed>
      <received>0</received>
    </history>
    <history>
      <id>9239</id>
      <alias>comment</alias>
      <memberId>5115</memberId>
      <performed>0</performed>
      <received>0</received>
    </history>
    <history>
      <id>10241</id>
      <alias>comment</alias>
      <memberId>5115</memberId>
      <performed>1</performed>
      <received>0</received>
    </history>
    <history>
      <id>10259</id>
      <alias>comment</alias>
      <memberId>5115</memberId>
      <performed>0</performed>
      <received>0</received>
    </history>
    <history>
      <id>11068</id>
      <alias>comment</alias>
      <memberId>5115</memberId>
      <performed>0</performed>
      <received>0</received>
    </history>
    <history>
      <id>12478</id>
      <alias>comment</alias>
      <memberId>5115</memberId>
      <performed>1</performed>
      <received>0</received>
    </history>
    <history>
      <id>12479</id>
      <alias>comment</alias>
      <memberId>5115</memberId>
      <performed>1</performed>
      <received>0</received>
    </history>
    <history>
      <id>12654</id>
      <alias>comment</alias>
      <memberId>5115</memberId>
      <performed>1</performed>
      <received>0</received>
    </history>
    <history>
      <id>12686</id>
      <alias>comment</alias>
      <memberId>5115</memberId>
      <performed>1</performed>
      <received>0</received>
    </history>
    <history>
      <id>14471</id>
      <alias>comment</alias>
      <memberId>5115</memberId>
      <performed>1</performed>
      <received>0</received>
    </history>
    <history>
      <id>14480</id>
      <alias>comment</alias>
      <memberId>5115</memberId>
      <performed>1</performed>
      <received>0</received>
    </history>
    <history>
      <id>14902</id>
      <alias>comment</alias>
      <memberId>5115</memberId>
      <performed>1</performed>
      <received>0</received>
    </history>
    <history>
      <id>14906</id>
      <alias>comment</alias>
      <memberId>5115</memberId>
      <performed>1</performed>
      <received>0</received>
    </history>
    <history>
      <id>14908</id>
      <alias>comment</alias>
      <memberId>5115</memberId>
      <performed>1</performed>
      <received>0</received>
    </history>
    <history>
      <id>14911</id>
      <alias>comment</alias>
      <memberId>5115</memberId>
      <performed>1</performed>
      <received>0</received>
    </history>
    <history>
      <id>15032</id>
      <alias>comment</alias>
      <memberId>5115</memberId>
      <performed>1</performed>
      <received>0</received>
    </history>
    <history>
      <id>3088</id>
      <alias>topic</alias>
      <memberId>5115</memberId>
      <performed>0</performed>
      <received>0</received>
    </history>
    <history>
      <id>3589</id>
      <alias>topic</alias>
      <memberId>5115</memberId>
      <performed>1</performed>
      <received>0</received>
    </history>
    <history>
      <id>3592</id>
      <alias>topic</alias>
      <memberId>5115</memberId>
      <performed>1</performed>
      <received>0</received>
    </history>
    <history>
      <id>4026</id>
      <alias>topic</alias>
      <memberId>5115</memberId>
      <performed>1</performed>
      <received>0</received>
    </history>
    <history>
      <id>4147</id>
      <alias>topic</alias>
      <memberId>5115</memberId>
      <performed>1</performed>
      <received>0</received>
    </history>
    <history>
      <id>4175</id>
      <alias>topic</alias>
      <memberId>5115</memberId>
      <performed>1</performed>
      <received>0</received>
    </history>
  </histories>
</karma>