<karma>
  <summaries>
    <summary>
      <alias>comment</alias>
      <memberId>5407</memberId>
      <performed>20</performed>
      <received>0</received>
    </summary>
    <summary>
      <alias>topic</alias>
      <memberId>5407</memberId>
      <performed>0</performed>
      <received>0</received>
    </summary>
  </summaries>
  <histories>
    <history>
      <id>10173</id>
      <alias>comment</alias>
      <memberId>5407</memberId>
      <performed>10</performed>
      <received>0</received>
    </history>
    <history>
      <id>10202</id>
      <alias>comment</alias>
      <memberId>5407</memberId>
      <performed>10</performed>
      <received>0</received>
    </history>
    <history>
      <id>3069</id>
      <alias>topic</alias>
      <memberId>5407</memberId>
      <performed>0</performed>
      <received>0</received>
    </history>
    <history>
      <id>3071</id>
      <alias>topic</alias>
      <memberId>5407</memberId>
      <performed>0</performed>
      <received>0</received>
    </history>
  </histories>
</karma>