<karma>
  <summaries>
    <summary>
      <alias>topic</alias>
      <memberId>6049</memberId>
      <performed>0</performed>
      <received>4</received>
    </summary>
    <summary>
      <alias>project</alias>
      <memberId>6049</memberId>
      <performed>0</performed>
      <received>30</received>
    </summary>
    <summary>
      <alias>comment</alias>
      <memberId>6049</memberId>
      <performed>0</performed>
      <received>1</received>
    </summary>
    <summary>
      <alias>comment</alias>
      <memberId>6049</memberId>
      <performed>26</performed>
      <received>0</received>
    </summary>
    <summary>
      <alias>project</alias>
      <memberId>6049</memberId>
      <performed>2</performed>
      <received>0</received>
    </summary>
    <summary>
      <alias>topic</alias>
      <memberId>6049</memberId>
      <performed>13</performed>
      <received>0</received>
    </summary>
  </summaries>
  <histories>
    <history>
      <id>7629</id>
      <alias>topic</alias>
      <memberId>6049</memberId>
      <performed>0</performed>
      <received>1</received>
    </history>
    <history>
      <id>9227</id>
      <alias>topic</alias>
      <memberId>6049</memberId>
      <performed>0</performed>
      <received>1</received>
    </history>
    <history>
      <id>10224</id>
      <alias>topic</alias>
      <memberId>6049</memberId>
      <performed>0</performed>
      <received>1</received>
    </history>
    <history>
      <id>10224</id>
      <alias>topic</alias>
      <memberId>6049</memberId>
      <performed>0</performed>
      <received>1</received>
    </history>
    <history>
      <id>7057</id>
      <alias>project</alias>
      <memberId>6049</memberId>
      <performed>0</performed>
      <received>5</received>
    </history>
    <history>
      <id>7566</id>
      <alias>project</alias>
      <memberId>6049</memberId>
      <performed>0</performed>
      <received>5</received>
    </history>
    <history>
      <id>7566</id>
      <alias>project</alias>
      <memberId>6049</memberId>
      <performed>0</performed>
      <received>5</received>
    </history>
    <history>
      <id>7566</id>
      <alias>project</alias>
      <memberId>6049</memberId>
      <performed>0</performed>
      <received>5</received>
    </history>
    <history>
      <id>8499</id>
      <alias>project</alias>
      <memberId>6049</memberId>
      <performed>0</performed>
      <received>5</received>
    </history>
    <history>
      <id>8499</id>
      <alias>project</alias>
      <memberId>6049</memberId>
      <performed>0</performed>
      <received>5</received>
    </history>
    <history>
      <id>29220</id>
      <alias>comment</alias>
      <memberId>6049</memberId>
      <performed>0</performed>
      <received>1</received>
    </history>
    <history>
      <id>26653</id>
      <alias>comment</alias>
      <memberId>6049</memberId>
      <performed>10</performed>
      <received>0</received>
    </history>
    <history>
      <id>27295</id>
      <alias>comment</alias>
      <memberId>6049</memberId>
      <performed>1</performed>
      <received>0</received>
    </history>
    <history>
      <id>27991</id>
      <alias>comment</alias>
      <memberId>6049</memberId>
      <performed>1</performed>
      <received>0</received>
    </history>
    <history>
      <id>28886</id>
      <alias>comment</alias>
      <memberId>6049</memberId>
      <performed>1</performed>
      <received>0</received>
    </history>
    <history>
      <id>29220</id>
      <alias>comment</alias>
      <memberId>6049</memberId>
      <performed>1</performed>
      <received>0</received>
    </history>
    <history>
      <id>33703</id>
      <alias>comment</alias>
      <memberId>6049</memberId>
      <performed>1</performed>
      <received>0</received>
    </history>
    <history>
      <id>33734</id>
      <alias>comment</alias>
      <memberId>6049</memberId>
      <performed>1</performed>
      <received>0</received>
    </history>
    <history>
      <id>34422</id>
      <alias>comment</alias>
      <memberId>6049</memberId>
      <performed>1</performed>
      <received>0</received>
    </history>
    <history>
      <id>36244</id>
      <alias>comment</alias>
      <memberId>6049</memberId>
      <performed>1</performed>
      <received>0</received>
    </history>
    <history>
      <id>36276</id>
      <alias>comment</alias>
      <memberId>6049</memberId>
      <performed>1</performed>
      <received>0</received>
    </history>
    <history>
      <id>36301</id>
      <alias>comment</alias>
      <memberId>6049</memberId>
      <performed>1</performed>
      <received>0</received>
    </history>
    <history>
      <id>36328</id>
      <alias>comment</alias>
      <memberId>6049</memberId>
      <performed>1</performed>
      <received>0</received>
    </history>
    <history>
      <id>37281</id>
      <alias>comment</alias>
      <memberId>6049</memberId>
      <performed>1</performed>
      <received>0</received>
    </history>
    <history>
      <id>37294</id>
      <alias>comment</alias>
      <memberId>6049</memberId>
      <performed>1</performed>
      <received>0</received>
    </history>
    <history>
      <id>37295</id>
      <alias>comment</alias>
      <memberId>6049</memberId>
      <performed>1</performed>
      <received>0</received>
    </history>
    <history>
      <id>37296</id>
      <alias>comment</alias>
      <memberId>6049</memberId>
      <performed>1</performed>
      <received>0</received>
    </history>
    <history>
      <id>37320</id>
      <alias>comment</alias>
      <memberId>6049</memberId>
      <performed>1</performed>
      <received>0</received>
    </history>
    <history>
      <id>4687</id>
      <alias>project</alias>
      <memberId>6049</memberId>
      <performed>1</performed>
      <received>0</received>
    </history>
    <history>
      <id>8761</id>
      <alias>project</alias>
      <memberId>6049</memberId>
      <performed>1</performed>
      <received>0</received>
    </history>
    <history>
      <id>3946</id>
      <alias>topic</alias>
      <memberId>6049</memberId>
      <performed>1</performed>
      <received>0</received>
    </history>
    <history>
      <id>4960</id>
      <alias>topic</alias>
      <memberId>6049</memberId>
      <performed>1</performed>
      <received>0</received>
    </history>
    <history>
      <id>6737</id>
      <alias>topic</alias>
      <memberId>6049</memberId>
      <performed>1</performed>
      <received>0</received>
    </history>
    <history>
      <id>7055</id>
      <alias>topic</alias>
      <memberId>6049</memberId>
      <performed>1</performed>
      <received>0</received>
    </history>
    <history>
      <id>7289</id>
      <alias>topic</alias>
      <memberId>6049</memberId>
      <performed>1</performed>
      <received>0</received>
    </history>
    <history>
      <id>7357</id>
      <alias>topic</alias>
      <memberId>6049</memberId>
      <performed>1</performed>
      <received>0</received>
    </history>
    <history>
      <id>7629</id>
      <alias>topic</alias>
      <memberId>6049</memberId>
      <performed>1</performed>
      <received>0</received>
    </history>
    <history>
      <id>7639</id>
      <alias>topic</alias>
      <memberId>6049</memberId>
      <performed>1</performed>
      <received>0</received>
    </history>
    <history>
      <id>9227</id>
      <alias>topic</alias>
      <memberId>6049</memberId>
      <performed>1</performed>
      <received>0</received>
    </history>
    <history>
      <id>9577</id>
      <alias>topic</alias>
      <memberId>6049</memberId>
      <performed>1</performed>
      <received>0</received>
    </history>
    <history>
      <id>10014</id>
      <alias>topic</alias>
      <memberId>6049</memberId>
      <performed>1</performed>
      <received>0</received>
    </history>
    <history>
      <id>10224</id>
      <alias>topic</alias>
      <memberId>6049</memberId>
      <performed>1</performed>
      <received>0</received>
    </history>
    <history>
      <id>10238</id>
      <alias>topic</alias>
      <memberId>6049</memberId>
      <performed>1</performed>
      <received>0</received>
    </history>
  </histories>
</karma>