<karma>
  <summaries>
    <summary>
      <alias>topic</alias>
      <memberId>6208</memberId>
      <performed>0</performed>
      <received>4</received>
    </summary>
    <summary>
      <alias>comment</alias>
      <memberId>6208</memberId>
      <performed>3</performed>
      <received>0</received>
    </summary>
    <summary>
      <alias>topic</alias>
      <memberId>6208</memberId>
      <performed>2</performed>
      <received>0</received>
    </summary>
  </summaries>
  <histories>
    <history>
      <id>4992</id>
      <alias>topic</alias>
      <memberId>6208</memberId>
      <performed>0</performed>
      <received>1</received>
    </history>
    <history>
      <id>4992</id>
      <alias>topic</alias>
      <memberId>6208</memberId>
      <performed>0</performed>
      <received>1</received>
    </history>
    <history>
      <id>4992</id>
      <alias>topic</alias>
      <memberId>6208</memberId>
      <performed>0</performed>
      <received>1</received>
    </history>
    <history>
      <id>4992</id>
      <alias>topic</alias>
      <memberId>6208</memberId>
      <performed>0</performed>
      <received>1</received>
    </history>
    <history>
      <id>18614</id>
      <alias>comment</alias>
      <memberId>6208</memberId>
      <performed>1</performed>
      <received>0</received>
    </history>
    <history>
      <id>20066</id>
      <alias>comment</alias>
      <memberId>6208</memberId>
      <performed>1</performed>
      <received>0</received>
    </history>
    <history>
      <id>33274</id>
      <alias>comment</alias>
      <memberId>6208</memberId>
      <performed>1</performed>
      <received>0</received>
    </history>
    <history>
      <id>4992</id>
      <alias>topic</alias>
      <memberId>6208</memberId>
      <performed>1</performed>
      <received>0</received>
    </history>
    <history>
      <id>9090</id>
      <alias>topic</alias>
      <memberId>6208</memberId>
      <performed>1</performed>
      <received>0</received>
    </history>
  </histories>
</karma>