<karma>
  <summaries>
    <summary>
      <alias>topic</alias>
      <memberId>7460</memberId>
      <performed>0</performed>
      <received>1</received>
    </summary>
    <summary>
      <alias>comment</alias>
      <memberId>7460</memberId>
      <performed>0</performed>
      <received>3</received>
    </summary>
    <summary>
      <alias>comment</alias>
      <memberId>7460</memberId>
      <performed>26</performed>
      <received>0</received>
    </summary>
    <summary>
      <alias>topic</alias>
      <memberId>7460</memberId>
      <performed>9</performed>
      <received>0</received>
    </summary>
  </summaries>
  <histories>
    <history>
      <id>7781</id>
      <alias>topic</alias>
      <memberId>7460</memberId>
      <performed>0</performed>
      <received>1</received>
    </history>
    <history>
      <id>28268</id>
      <alias>comment</alias>
      <memberId>7460</memberId>
      <performed>0</performed>
      <received>1</received>
    </history>
    <history>
      <id>28575</id>
      <alias>comment</alias>
      <memberId>7460</memberId>
      <performed>0</performed>
      <received>1</received>
    </history>
    <history>
      <id>33782</id>
      <alias>comment</alias>
      <memberId>7460</memberId>
      <performed>0</performed>
      <received>1</received>
    </history>
    <history>
      <id>27517</id>
      <alias>comment</alias>
      <memberId>7460</memberId>
      <performed>1</performed>
      <received>0</received>
    </history>
    <history>
      <id>28180</id>
      <alias>comment</alias>
      <memberId>7460</memberId>
      <performed>1</performed>
      <received>0</received>
    </history>
    <history>
      <id>28183</id>
      <alias>comment</alias>
      <memberId>7460</memberId>
      <performed>1</performed>
      <received>0</received>
    </history>
    <history>
      <id>28185</id>
      <alias>comment</alias>
      <memberId>7460</memberId>
      <performed>1</performed>
      <received>0</received>
    </history>
    <history>
      <id>28190</id>
      <alias>comment</alias>
      <memberId>7460</memberId>
      <performed>1</performed>
      <received>0</received>
    </history>
    <history>
      <id>28192</id>
      <alias>comment</alias>
      <memberId>7460</memberId>
      <performed>1</performed>
      <received>0</received>
    </history>
    <history>
      <id>28196</id>
      <alias>comment</alias>
      <memberId>7460</memberId>
      <performed>1</performed>
      <received>0</received>
    </history>
    <history>
      <id>28197</id>
      <alias>comment</alias>
      <memberId>7460</memberId>
      <performed>1</performed>
      <received>0</received>
    </history>
    <history>
      <id>28225</id>
      <alias>comment</alias>
      <memberId>7460</memberId>
      <performed>1</performed>
      <received>0</received>
    </history>
    <history>
      <id>28226</id>
      <alias>comment</alias>
      <memberId>7460</memberId>
      <performed>1</performed>
      <received>0</received>
    </history>
    <history>
      <id>28268</id>
      <alias>comment</alias>
      <memberId>7460</memberId>
      <performed>1</performed>
      <received>0</received>
    </history>
    <history>
      <id>28472</id>
      <alias>comment</alias>
      <memberId>7460</memberId>
      <performed>1</performed>
      <received>0</received>
    </history>
    <history>
      <id>28575</id>
      <alias>comment</alias>
      <memberId>7460</memberId>
      <performed>1</performed>
      <received>0</received>
    </history>
    <history>
      <id>28669</id>
      <alias>comment</alias>
      <memberId>7460</memberId>
      <performed>1</performed>
      <received>0</received>
    </history>
    <history>
      <id>28670</id>
      <alias>comment</alias>
      <memberId>7460</memberId>
      <performed>1</performed>
      <received>0</received>
    </history>
    <history>
      <id>28671</id>
      <alias>comment</alias>
      <memberId>7460</memberId>
      <performed>1</performed>
      <received>0</received>
    </history>
    <history>
      <id>28676</id>
      <alias>comment</alias>
      <memberId>7460</memberId>
      <performed>1</performed>
      <received>0</received>
    </history>
    <history>
      <id>28677</id>
      <alias>comment</alias>
      <memberId>7460</memberId>
      <performed>1</performed>
      <received>0</received>
    </history>
    <history>
      <id>28704</id>
      <alias>comment</alias>
      <memberId>7460</memberId>
      <performed>1</performed>
      <received>0</received>
    </history>
    <history>
      <id>28913</id>
      <alias>comment</alias>
      <memberId>7460</memberId>
      <performed>1</performed>
      <received>0</received>
    </history>
    <history>
      <id>28915</id>
      <alias>comment</alias>
      <memberId>7460</memberId>
      <performed>1</performed>
      <received>0</received>
    </history>
    <history>
      <id>29224</id>
      <alias>comment</alias>
      <memberId>7460</memberId>
      <performed>1</performed>
      <received>0</received>
    </history>
    <history>
      <id>33765</id>
      <alias>comment</alias>
      <memberId>7460</memberId>
      <performed>1</performed>
      <received>0</received>
    </history>
    <history>
      <id>33782</id>
      <alias>comment</alias>
      <memberId>7460</memberId>
      <performed>1</performed>
      <received>0</received>
    </history>
    <history>
      <id>35927</id>
      <alias>comment</alias>
      <memberId>7460</memberId>
      <performed>1</performed>
      <received>0</received>
    </history>
    <history>
      <id>36759</id>
      <alias>comment</alias>
      <memberId>7460</memberId>
      <performed>1</performed>
      <received>0</received>
    </history>
    <history>
      <id>7484</id>
      <alias>topic</alias>
      <memberId>7460</memberId>
      <performed>1</performed>
      <received>0</received>
    </history>
    <history>
      <id>7668</id>
      <alias>topic</alias>
      <memberId>7460</memberId>
      <performed>1</performed>
      <received>0</received>
    </history>
    <history>
      <id>7738</id>
      <alias>topic</alias>
      <memberId>7460</memberId>
      <performed>1</performed>
      <received>0</received>
    </history>
    <history>
      <id>7756</id>
      <alias>topic</alias>
      <memberId>7460</memberId>
      <performed>1</performed>
      <received>0</received>
    </history>
    <history>
      <id>7757</id>
      <alias>topic</alias>
      <memberId>7460</memberId>
      <performed>1</performed>
      <received>0</received>
    </history>
    <history>
      <id>7777</id>
      <alias>topic</alias>
      <memberId>7460</memberId>
      <performed>1</performed>
      <received>0</received>
    </history>
    <history>
      <id>7781</id>
      <alias>topic</alias>
      <memberId>7460</memberId>
      <performed>1</performed>
      <received>0</received>
    </history>
    <history>
      <id>7858</id>
      <alias>topic</alias>
      <memberId>7460</memberId>
      <performed>1</performed>
      <received>0</received>
    </history>
    <history>
      <id>7937</id>
      <alias>topic</alias>
      <memberId>7460</memberId>
      <performed>1</performed>
      <received>0</received>
    </history>
  </histories>
</karma>