<karma>
  <summaries>
    <summary>
      <alias>comment</alias>
      <memberId>7617</memberId>
      <performed>8</performed>
      <received>0</received>
    </summary>
    <summary>
      <alias>topic</alias>
      <memberId>7617</memberId>
      <performed>8</performed>
      <received>0</received>
    </summary>
  </summaries>
  <histories>
    <history>
      <id>28825</id>
      <alias>comment</alias>
      <memberId>7617</memberId>
      <performed>1</performed>
      <received>0</received>
    </history>
    <history>
      <id>28827</id>
      <alias>comment</alias>
      <memberId>7617</memberId>
      <performed>1</performed>
      <received>0</received>
    </history>
    <history>
      <id>28829</id>
      <alias>comment</alias>
      <memberId>7617</memberId>
      <performed>1</performed>
      <received>0</received>
    </history>
    <history>
      <id>31841</id>
      <alias>comment</alias>
      <memberId>7617</memberId>
      <performed>1</performed>
      <received>0</received>
    </history>
    <history>
      <id>31842</id>
      <alias>comment</alias>
      <memberId>7617</memberId>
      <performed>1</performed>
      <received>0</received>
    </history>
    <history>
      <id>32274</id>
      <alias>comment</alias>
      <memberId>7617</memberId>
      <performed>1</performed>
      <received>0</received>
    </history>
    <history>
      <id>32278</id>
      <alias>comment</alias>
      <memberId>7617</memberId>
      <performed>1</performed>
      <received>0</received>
    </history>
    <history>
      <id>32305</id>
      <alias>comment</alias>
      <memberId>7617</memberId>
      <performed>1</performed>
      <received>0</received>
    </history>
    <history>
      <id>7817</id>
      <alias>topic</alias>
      <memberId>7617</memberId>
      <performed>1</performed>
      <received>0</received>
    </history>
    <history>
      <id>7830</id>
      <alias>topic</alias>
      <memberId>7617</memberId>
      <performed>1</performed>
      <received>0</received>
    </history>
    <history>
      <id>7831</id>
      <alias>topic</alias>
      <memberId>7617</memberId>
      <performed>1</performed>
      <received>0</received>
    </history>
    <history>
      <id>8291</id>
      <alias>topic</alias>
      <memberId>7617</memberId>
      <performed>1</performed>
      <received>0</received>
    </history>
    <history>
      <id>8606</id>
      <alias>topic</alias>
      <memberId>7617</memberId>
      <performed>1</performed>
      <received>0</received>
    </history>
    <history>
      <id>8638</id>
      <alias>topic</alias>
      <memberId>7617</memberId>
      <performed>1</performed>
      <received>0</received>
    </history>
    <history>
      <id>8844</id>
      <alias>topic</alias>
      <memberId>7617</memberId>
      <performed>1</performed>
      <received>0</received>
    </history>
    <history>
      <id>8845</id>
      <alias>topic</alias>
      <memberId>7617</memberId>
      <performed>1</performed>
      <received>0</received>
    </history>
  </histories>
</karma>