<karma>
  <summaries>
    <summary>
      <alias>comment</alias>
      <memberId>8482</memberId>
      <performed>3</performed>
      <received>0</received>
    </summary>
  </summaries>
  <histories>
    <history>
      <id>36178</id>
      <alias>comment</alias>
      <memberId>8482</memberId>
      <performed>1</performed>
      <received>0</received>
    </history>
    <history>
      <id>36227</id>
      <alias>comment</alias>
      <memberId>8482</memberId>
      <performed>1</performed>
      <received>0</received>
    </history>
    <history>
      <id>37243</id>
      <alias>comment</alias>
      <memberId>8482</memberId>
      <performed>1</performed>
      <received>0</received>
    </history>
  </histories>
</karma>